incremental_tasks/__init__.py
incremental_tasks/_version.py
incremental_tasks/base.py
incremental_tasks/cli.py
incremental_tasks/language.py
incremental_tasks/periodic.py
incremental_tasks/symbolic.py
incremental_tasks-0.1.3.dist-info/entry_points.txt
incremental_tasks-0.1.3.dist-info/LICENSE
incremental_tasks-0.1.3.dist-info/WHEEL
incremental_tasks-0.1.3.dist-info/METADATA
incremental_tasks-0.1.3.dist-info/RECORD
